networkh3
