Metadata-Version: 2.1
Name: networkh3
Version: 0.0.5
Summary: A package to return H3 hexagons based on an OSMnx network
Home-page: https://github.com/callumscoby/networkh3
Author: Callum Scoby
Author-email: callumjamesscoby@gmail.com
License: MIT
Keywords: OSMnx,H3,Routing,Network analysis
Classifier: Development Status :: 5 - Production/Stable
Classifier: Operating System :: OS Independent
Classifier: License :: OSI Approved :: MIT License
Classifier: Programming Language :: Python :: 3
License-File: LICENSE.txt
